<?xml version="1.0" encoding="utf-8" ?>
<dwsync>
<file name="info.html" server="D:/wamp/bin/apache/Apache2.4.4" local="131594416491286270" remote="131594416490000000" Dst="0" />
<file name="conn.php" server="D:/wamp/bin/apache/Apache2.4.4" local="131594428840544310" remote="131594428840000000" Dst="0" />
<file name="function.php" server="D:/wamp/bin/apache/Apache2.4.4" local="131419688660000000" remote="131419688660000000" Dst="0" />
<file name="login.php" server="D:/wamp/bin/apache/Apache2.4.4" local="131594604078731563" remote="131594604070000000" Dst="0" />
<file name="code.php" server="D:/wamp/bin/apache/Apache2.4.4" local="131594614605313649" remote="131594614600000000" Dst="0" />
<file name="login.html" server="D:/wamp/bin/apache/Apache2.4.4" local="131594610897021547" remote="131594610890000000" Dst="0" />
<file name="select_save.php" server="D:/wamp/bin/apache/Apache2.4.4" local="131594236463002506" remote="131594236460000000" Dst="0" />
<file name="course_list.php" server="D:/wamp/bin/apache/Apache2.4.4" local="131593755838354867" remote="131593755830000000" Dst="0" />
<file name="select.php" server="D:/wamp/bin/apache/Apache2.4.4" local="131594207765611006" remote="131594207760000000" Dst="0" />
<file name="student_index.php" server="D:/wamp/bin/apache/Apache2.4.4" local="131594402195818659" remote="131594402190000000" Dst="0" />
<file name="tea_index.php" server="D:/wamp/bin/apache/Apache2.4.4" local="131595418438991518" remote="131595418430000000" Dst="0" />
<file name="res.php" server="D:/wamp/bin/apache/Apache2.4.4" local="131594456441796252" remote="131594456440000000" Dst="0" />
<file name="index.php" server="D:/wamp/bin/apache/Apache2.4.4" local="131596096177732983" remote="131596096170000000" Dst="0" />
</dwsync>